csutils/__init__.py
csutils/combined_payment_schedule.py
csutils/compliance_report.py
csutils/payment_schedule.py
csutils/payments_made.py
csutils/stepdown.py
csutils-0.1.9.dist-info/LICENSE
csutils-0.1.9.dist-info/METADATA
csutils-0.1.9.dist-info/WHEEL
csutils-0.1.9.dist-info/top_level.txt
csutils-0.1.9.dist-info/RECORD
