Metadata-Version: 2.1
Name: csutils
Version: 0.1.9
Summary: Child Support Utilities
Home-page: https://github.com/tjdaley/csutils
Author: Thomas J. Daley, J.D.
Author-email: tom@powerdaley.com
License: BSD-3-Clause License
Platform: UNKNOWN
